adbscripts/README.MD
adbscripts/__init__.py
adbscripts/chromewebscraping.py
adbscripts/coloratpixeloncerep.py
adbscripts/getactivityelements.py
adbscripts/getcoloratpixel.py
adbscripts/getuiautomator.py
adbscripts/requirements.txt
adbscripts/thirdparty.json
adbscripts-0.11.dist-info/LICENSE.rst
adbscripts-0.11.dist-info/METADATA
adbscripts-0.11.dist-info/WHEEL
adbscripts-0.11.dist-info/top_level.txt
adbscripts-0.11.dist-info/RECORD
