Metadata-Version: 2.1
Name: adbscripts
Version: 0.11
Summary: some adb scripts
Home-page: https://github.com/hansalemaos/adbscripts
Author: Johannes Fischer
Author-email: aulasparticularesdealemaosp@gmail.com
License: MIT
Keywords: adb,scripts
Classifier: Development Status :: 4 - Beta
Classifier: Programming Language :: Python :: 3 :: Only
Classifier: Programming Language :: Python :: 3.10
Classifier: Topic :: Software Development :: Libraries :: Python Modules
Classifier: Topic :: Utilities
License-File: LICENSE.rst
Requires-Dist: kthread
Requires-Dist: psutil
